{
    "timestamp": "2026-03-27 12:29:54",
    "seed": 967021568,
    "status": "Succes",
    "generationTimeMs": 6.332099914550781,
    "config": {
        "mapWidth": 30,
        "mapHeight": 30,
        "cellSize": 6.0,
        "minRooms": 5,
        "maxRooms": 12,
        "mode": "Complet",
        "enabledCategories": [
            "Sols",
            "Eau",
            "Arbres",
            "Buissons",
            "Herbe",
            "Fleurs",
            "RochesDures",
            "RochesTendres",
            "Cactus",
            "Champignons",
            "Minerais",
            "Gemmes",
            "Troncs",
            "Epines",
            "Feuillage",
            "Debris",
            "Coraux"
        ]
    },
    "results": {
        "roomCount": 12,
        "corridorCount": 11,
        "totalObjectsPlaced": 805,
        "walkableCells": 248,
        "wallCells": 428,
        "spawnCell": "4,6",
        "exitCell": "24,9",
        "spawnToExitDistance": 121.34249877929688
    },
    "errors": 0,
    "warnings": 0,
    "validationEntries": [
        "[INFO] SpawnValide: Spawn valide à (4,6) @(4,6)",
        "[INFO] Connectivité: Map entièrement connectée (248 cellules)",
        "[INFO] CheminSpawnExit: Chemin trouvé: 24 cellules (144 unités)"
    ],
    "pipeline": [
        "[12:29:54.059] Initialisation de la grille",
        "[12:29:54.059] Grille 30x30 initialisée (tout en Mur)",
        "[12:29:54.059] Génération des salles (BSP)",
        "[12:29:54.060] 12 salles générées sur 6 ciblées",
        "[12:29:54.061] Connexion des salles (couloirs)",
        "[12:29:54.062] 11 couloirs créés",
        "[12:29:54.062] Attribution des biomes",
        "[12:29:54.062] Biomes assignés par bruit de Perlin + cohérence par salle",
        "[12:29:54.063] Placement du spawn et de la sortie",
        "[12:29:54.063] Spawn: (4,6), Sortie: (24,9), Distance: 121,3",
        "[12:29:54.063] Finalisation de la map",
        "[12:29:54.065] Map finalisée",
        "[12:29:54.065] Placement des assets",
        "[12:29:54.066] Début du placement des assets",
        "[12:29:54.141] Placement terminé: 805 objets",
        "[12:29:54.141]   Sols: 321",
        "[12:29:54.141]   Buissons: 89",
        "[12:29:54.141]   Arbres: 141",
        "[12:29:54.141]   Troncs: 24",
        "[12:29:54.141]   RochesDures: 12",
        "[12:29:54.141]   RochesTendres: 120",
        "[12:29:54.141]   Herbe: 31",
        "[12:29:54.141]   Feuillage: 12",
        "[12:29:54.141]   Fleurs: 21",
        "[12:29:54.141]   Champignons: 20",
        "[12:29:54.141]   Debris: 5",
        "[12:29:54.141]   Gemmes: 1",
        "[12:29:54.141]   Minerais: 6",
        "[12:29:54.141]   Cactus: 2",
        "[12:29:54.147] Validation terminée: SUCCES (0E / 0W / 3I)"
    ]
}